{
  "AttributesData": [
    {
      "ElementType": "DocumentFormat.OpenXml.Wordprocessing.Document",
      "AttributeType": "DocumentFormat.OpenXml.StringValue",
      "Name": {
        "Name": "IgnorablePrefixes",
        "XmlName": "Ignorable",
        "NamespaceUri": "http://schemas.openxmlformats.org/markup-compatibility/2006",
        "NamespacePrefix": "mc"
      }
    },
    {
      "ElementType": "DocumentFormat.OpenXml.Wordprocessing.Document",
      "AttributeType": "DocumentFormat.OpenXml.EnumValue\u00601[[DocumentFormat.OpenXml.Wordprocessing.DocumentConformance, DocumentFormat.OpenXml, Version=2.15.0.0, Culture=neutral, PublicKeyToken=8fb06cb64d019a17]]",
      "Name": {
        "Name": "Conformance",
        "XmlName": "conformance",
        "NamespaceUri": "http://schemas.openxmlformats.org/wordprocessingml/2006/main",
        "NamespacePrefix": "w"
      }
    },
    {
      "ElementType": "DocumentFormat.OpenXml.Wordprocessing.Paragraph",
      "AttributeType": "DocumentFormat.OpenXml.HexBinaryValue",
      "Name": {
        "Name": "RsidParagraphMarkRevision",
        "XmlName": "rsidRPr",
        "NamespaceUri": "http://schemas.openxmlformats.org/wordprocessingml/2006/main",
        "NamespacePrefix": "w"
      }
    },
    {
      "ElementType": "DocumentFormat.OpenXml.Wordprocessing.Paragraph",
      "AttributeType": "DocumentFormat.OpenXml.HexBinaryValue",
      "Name": {
        "Name": "RsidParagraphAddition",
        "XmlName": "rsidR",
        "NamespaceUri": "http://schemas.openxmlformats.org/wordprocessingml/2006/main",
        "NamespacePrefix": "w"
      }
    },
    {
      "ElementType": "DocumentFormat.OpenXml.Wordprocessing.Paragraph",
      "AttributeType": "DocumentFormat.OpenXml.HexBinaryValue",
      "Name": {
        "Name": "RsidParagraphDeletion",
        "XmlName": "rsidDel",
        "NamespaceUri": "http://schemas.openxmlformats.org/wordprocessingml/2006/main",
        "NamespacePrefix": "w"
      }
    },
    {
      "ElementType": "DocumentFormat.OpenXml.Wordprocessing.Paragraph",
      "AttributeType": "DocumentFormat.OpenXml.HexBinaryValue",
      "Name": {
        "Name": "RsidParagraphProperties",
        "XmlName": "rsidP",
        "NamespaceUri": "http://schemas.openxmlformats.org/wordprocessingml/2006/main",
        "NamespacePrefix": "w"
      }
    },
    {
      "ElementType": "DocumentFormat.OpenXml.Wordprocessing.Paragraph",
      "AttributeType": "DocumentFormat.OpenXml.HexBinaryValue",
      "Name": {
        "Name": "RsidRunAdditionDefault",
        "XmlName": "rsidRDefault",
        "NamespaceUri": "http://schemas.openxmlformats.org/wordprocessingml/2006/main",
        "NamespacePrefix": "w"
      }
    },
    {
      "ElementType": "DocumentFormat.OpenXml.Wordprocessing.Paragraph",
      "AttributeType": "DocumentFormat.OpenXml.HexBinaryValue",
      "Name": {
        "Name": "ParagraphId",
        "XmlName": "paraId",
        "NamespaceUri": "http://schemas.microsoft.com/office/word/2010/wordml",
        "NamespacePrefix": "w14"
      }
    },
    {
      "ElementType": "DocumentFormat.OpenXml.Wordprocessing.Paragraph",
      "AttributeType": "DocumentFormat.OpenXml.HexBinaryValue",
      "Name": {
        "Name": "TextId",
        "XmlName": "textId",
        "NamespaceUri": "http://schemas.microsoft.com/office/word/2010/wordml",
        "NamespacePrefix": "w14"
      }
    },
    {
      "ElementType": "DocumentFormat.OpenXml.Wordprocessing.Paragraph",
      "AttributeType": "DocumentFormat.OpenXml.OnOffValue",
      "Name": {
        "Name": "NoSpellError",
        "XmlName": "noSpellErr",
        "NamespaceUri": "http://schemas.microsoft.com/office/word/2010/wordml",
        "NamespacePrefix": "w14"
      }
    },
    {
      "ElementType": "DocumentFormat.OpenXml.Wordprocessing.ParagraphStyleId",
      "AttributeType": "DocumentFormat.OpenXml.StringValue",
      "Name": {
        "Name": "Val",
        "XmlName": "val",
        "NamespaceUri": "http://schemas.openxmlformats.org/wordprocessingml/2006/main",
        "NamespacePrefix": "w"
      }
    },
    {
      "ElementType": "DocumentFormat.OpenXml.Wordprocessing.BiDi",
      "AttributeType": "DocumentFormat.OpenXml.OnOffValue",
      "Name": {
        "Name": "Val",
        "XmlName": "val",
        "NamespaceUri": "http://schemas.openxmlformats.org/wordprocessingml/2006/main",
        "NamespacePrefix": "w"
      }
    },
    {
      "ElementType": "DocumentFormat.OpenXml.Wordprocessing.Justification",
      "AttributeType": "DocumentFormat.OpenXml.EnumValue\u00601[[DocumentFormat.OpenXml.Wordprocessing.JustificationValues, DocumentFormat.OpenXml, Version=2.15.0.0, Culture=neutral, PublicKeyToken=8fb06cb64d019a17]]",
      "Name": {
        "Name": "Val",
        "XmlName": "val",
        "NamespaceUri": "http://schemas.openxmlformats.org/wordprocessingml/2006/main",
        "NamespacePrefix": "w"
      }
    },
    {
      "ElementType": "DocumentFormat.OpenXml.Wordprocessing.Run",
      "AttributeType": "DocumentFormat.OpenXml.HexBinaryValue",
      "Name": {
        "Name": "RsidRunProperties",
        "XmlName": "rsidRPr",
        "NamespaceUri": "http://schemas.openxmlformats.org/wordprocessingml/2006/main",
        "NamespacePrefix": "w"
      }
    },
    {
      "ElementType": "DocumentFormat.OpenXml.Wordprocessing.Run",
      "AttributeType": "DocumentFormat.OpenXml.HexBinaryValue",
      "Name": {
        "Name": "RsidRunDeletion",
        "XmlName": "rsidDel",
        "NamespaceUri": "http://schemas.openxmlformats.org/wordprocessingml/2006/main",
        "NamespacePrefix": "w"
      }
    },
    {
      "ElementType": "DocumentFormat.OpenXml.Wordprocessing.Run",
      "AttributeType": "DocumentFormat.OpenXml.HexBinaryValue",
      "Name": {
        "Name": "RsidRunAddition",
        "XmlName": "rsidR",
        "NamespaceUri": "http://schemas.openxmlformats.org/wordprocessingml/2006/main",
        "NamespacePrefix": "w"
      }
    },
    {
      "ElementType": "DocumentFormat.OpenXml.Wordprocessing.RightToLeftText",
      "AttributeType": "DocumentFormat.OpenXml.OnOffValue",
      "Name": {
        "Name": "Val",
        "XmlName": "val",
        "NamespaceUri": "http://schemas.openxmlformats.org/wordprocessingml/2006/main",
        "NamespacePrefix": "w"
      }
    },
    {
      "ElementType": "DocumentFormat.OpenXml.Wordprocessing.Text",
      "AttributeType": "DocumentFormat.OpenXml.EnumValue\u00601[[DocumentFormat.OpenXml.SpaceProcessingModeValues, DocumentFormat.OpenXml, Version=2.15.0.0, Culture=neutral, PublicKeyToken=8fb06cb64d019a17]]",
      "Name": {
        "Name": "Space",
        "XmlName": "space",
        "NamespaceUri": "http://www.w3.org/XML/1998/namespace",
        "NamespacePrefix": "xml"
      }
    },
    {
      "ElementType": "DocumentFormat.OpenXml.Wordprocessing.Bold",
      "AttributeType": "DocumentFormat.OpenXml.OnOffValue",
      "Name": {
        "Name": "Val",
        "XmlName": "val",
        "NamespaceUri": "http://schemas.openxmlformats.org/wordprocessingml/2006/main",
        "NamespacePrefix": "w"
      }
    },
    {
      "ElementType": "DocumentFormat.OpenXml.Wordprocessing.BoldComplexScript",
      "AttributeType": "DocumentFormat.OpenXml.OnOffValue",
      "Name": {
        "Name": "Val",
        "XmlName": "val",
        "NamespaceUri": "http://schemas.openxmlformats.org/wordprocessingml/2006/main",
        "NamespacePrefix": "w"
      }
    },
    {
      "ElementType": "DocumentFormat.OpenXml.Wordprocessing.SectionProperties",
      "AttributeType": "DocumentFormat.OpenXml.HexBinaryValue",
      "Name": {
        "Name": "RsidRPr",
        "XmlName": "rsidRPr",
        "NamespaceUri": "http://schemas.openxmlformats.org/wordprocessingml/2006/main",
        "NamespacePrefix": "w"
      }
    },
    {
      "ElementType": "DocumentFormat.OpenXml.Wordprocessing.SectionProperties",
      "AttributeType": "DocumentFormat.OpenXml.HexBinaryValue",
      "Name": {
        "Name": "RsidDel",
        "XmlName": "rsidDel",
        "NamespaceUri": "http://schemas.openxmlformats.org/wordprocessingml/2006/main",
        "NamespacePrefix": "w"
      }
    },
    {
      "ElementType": "DocumentFormat.OpenXml.Wordprocessing.SectionProperties",
      "AttributeType": "DocumentFormat.OpenXml.HexBinaryValue",
      "Name": {
        "Name": "RsidR",
        "XmlName": "rsidR",
        "NamespaceUri": "http://schemas.openxmlformats.org/wordprocessingml/2006/main",
        "NamespacePrefix": "w"
      }
    },
    {
      "ElementType": "DocumentFormat.OpenXml.Wordprocessing.SectionProperties",
      "AttributeType": "DocumentFormat.OpenXml.HexBinaryValue",
      "Name": {
        "Name": "RsidSect",
        "XmlName": "rsidSect",
        "NamespaceUri": "http://schemas.openxmlformats.org/wordprocessingml/2006/main",
        "NamespacePrefix": "w"
      }
    },
    {
      "ElementType": "DocumentFormat.OpenXml.Wordprocessing.SectionType",
      "AttributeType": "DocumentFormat.OpenXml.EnumValue\u00601[[DocumentFormat.OpenXml.Wordprocessing.SectionMarkValues, DocumentFormat.OpenXml, Version=2.15.0.0, Culture=neutral, PublicKeyToken=8fb06cb64d019a17]]",
      "Name": {
        "Name": "Val",
        "XmlName": "val",
        "NamespaceUri": "http://schemas.openxmlformats.org/wordprocessingml/2006/main",
        "NamespacePrefix": "w"
      }
    },
    {
      "ElementType": "DocumentFormat.OpenXml.Wordprocessing.PageSize",
      "AttributeType": "DocumentFormat.OpenXml.UInt32Value",
      "Name": {
        "Name": "Width",
        "XmlName": "w",
        "NamespaceUri": "http://schemas.openxmlformats.org/wordprocessingml/2006/main",
        "NamespacePrefix": "w"
      }
    },
    {
      "ElementType": "DocumentFormat.OpenXml.Wordprocessing.PageSize",
      "AttributeType": "DocumentFormat.OpenXml.UInt32Value",
      "Name": {
        "Name": "Height",
        "XmlName": "h",
        "NamespaceUri": "http://schemas.openxmlformats.org/wordprocessingml/2006/main",
        "NamespacePrefix": "w"
      }
    },
    {
      "ElementType": "DocumentFormat.OpenXml.Wordprocessing.PageSize",
      "AttributeType": "DocumentFormat.OpenXml.EnumValue\u00601[[DocumentFormat.OpenXml.Wordprocessing.PageOrientationValues, DocumentFormat.OpenXml, Version=2.15.0.0, Culture=neutral, PublicKeyToken=8fb06cb64d019a17]]",
      "Name": {
        "Name": "Orient",
        "XmlName": "orient",
        "NamespaceUri": "http://schemas.openxmlformats.org/wordprocessingml/2006/main",
        "NamespacePrefix": "w"
      }
    },
    {
      "ElementType": "DocumentFormat.OpenXml.Wordprocessing.PageSize",
      "AttributeType": "DocumentFormat.OpenXml.UInt16Value",
      "Name": {
        "Name": "Code",
        "XmlName": "code",
        "NamespaceUri": "http://schemas.openxmlformats.org/wordprocessingml/2006/main",
        "NamespacePrefix": "w"
      }
    },
    {
      "ElementType": "DocumentFormat.OpenXml.Wordprocessing.PageMargin",
      "AttributeType": "DocumentFormat.OpenXml.Int32Value",
      "Name": {
        "Name": "Top",
        "XmlName": "top",
        "NamespaceUri": "http://schemas.openxmlformats.org/wordprocessingml/2006/main",
        "NamespacePrefix": "w"
      }
    },
    {
      "ElementType": "DocumentFormat.OpenXml.Wordprocessing.PageMargin",
      "AttributeType": "DocumentFormat.OpenXml.UInt32Value",
      "Name": {
        "Name": "Right",
        "XmlName": "right",
        "NamespaceUri": "http://schemas.openxmlformats.org/wordprocessingml/2006/main",
        "NamespacePrefix": "w"
      }
    },
    {
      "ElementType": "DocumentFormat.OpenXml.Wordprocessing.PageMargin",
      "AttributeType": "DocumentFormat.OpenXml.Int32Value",
      "Name": {
        "Name": "Bottom",
        "XmlName": "bottom",
        "NamespaceUri": "http://schemas.openxmlformats.org/wordprocessingml/2006/main",
        "NamespacePrefix": "w"
      }
    },
    {
      "ElementType": "DocumentFormat.OpenXml.Wordprocessing.PageMargin",
      "AttributeType": "DocumentFormat.OpenXml.UInt32Value",
      "Name": {
        "Name": "Left",
        "XmlName": "left",
        "NamespaceUri": "http://schemas.openxmlformats.org/wordprocessingml/2006/main",
        "NamespacePrefix": "w"
      }
    },
    {
      "ElementType": "DocumentFormat.OpenXml.Wordprocessing.PageMargin",
      "AttributeType": "DocumentFormat.OpenXml.UInt32Value",
      "Name": {
        "Name": "Header",
        "XmlName": "header",
        "NamespaceUri": "http://schemas.openxmlformats.org/wordprocessingml/2006/main",
        "NamespacePrefix": "w"
      }
    },
    {
      "ElementType": "DocumentFormat.OpenXml.Wordprocessing.PageMargin",
      "AttributeType": "DocumentFormat.OpenXml.UInt32Value",
      "Name": {
        "Name": "Footer",
        "XmlName": "footer",
        "NamespaceUri": "http://schemas.openxmlformats.org/wordprocessingml/2006/main",
        "NamespacePrefix": "w"
      }
    },
    {
      "ElementType": "DocumentFormat.OpenXml.Wordprocessing.PageMargin",
      "AttributeType": "DocumentFormat.OpenXml.UInt32Value",
      "Name": {
        "Name": "Gutter",
        "XmlName": "gutter",
        "NamespaceUri": "http://schemas.openxmlformats.org/wordprocessingml/2006/main",
        "NamespacePrefix": "w"
      }
    },
    {
      "ElementType": "DocumentFormat.OpenXml.Wordprocessing.PageNumberType",
      "AttributeType": "DocumentFormat.OpenXml.EnumValue\u00601[[DocumentFormat.OpenXml.Wordprocessing.NumberFormatValues, DocumentFormat.OpenXml, Version=2.15.0.0, Culture=neutral, PublicKeyToken=8fb06cb64d019a17]]",
      "Name": {
        "Name": "Format",
        "XmlName": "fmt",
        "NamespaceUri": "http://schemas.openxmlformats.org/wordprocessingml/2006/main",
        "NamespacePrefix": "w"
      }
    },
    {
      "ElementType": "DocumentFormat.OpenXml.Wordprocessing.PageNumberType",
      "AttributeType": "DocumentFormat.OpenXml.Int32Value",
      "Name": {
        "Name": "Start",
        "XmlName": "start",
        "NamespaceUri": "http://schemas.openxmlformats.org/wordprocessingml/2006/main",
        "NamespacePrefix": "w"
      }
    },
    {
      "ElementType": "DocumentFormat.OpenXml.Wordprocessing.PageNumberType",
      "AttributeType": "DocumentFormat.OpenXml.ByteValue",
      "Name": {
        "Name": "ChapterStyle",
        "XmlName": "chapStyle",
        "NamespaceUri": "http://schemas.openxmlformats.org/wordprocessingml/2006/main",
        "NamespacePrefix": "w"
      }
    },
    {
      "ElementType": "DocumentFormat.OpenXml.Wordprocessing.PageNumberType",
      "AttributeType": "DocumentFormat.OpenXml.EnumValue\u00601[[DocumentFormat.OpenXml.Wordprocessing.ChapterSeparatorValues, DocumentFormat.OpenXml, Version=2.15.0.0, Culture=neutral, PublicKeyToken=8fb06cb64d019a17]]",
      "Name": {
        "Name": "ChapterSeparator",
        "XmlName": "chapSep",
        "NamespaceUri": "http://schemas.openxmlformats.org/wordprocessingml/2006/main",
        "NamespacePrefix": "w"
      }
    },
    {
      "ElementType": "DocumentFormat.OpenXml.Wordprocessing.FormProtection",
      "AttributeType": "DocumentFormat.OpenXml.OnOffValue",
      "Name": {
        "Name": "Val",
        "XmlName": "val",
        "NamespaceUri": "http://schemas.openxmlformats.org/wordprocessingml/2006/main",
        "NamespacePrefix": "w"
      }
    },
    {
      "ElementType": "DocumentFormat.OpenXml.Wordprocessing.TextDirection",
      "AttributeType": "DocumentFormat.OpenXml.EnumValue\u00601[[DocumentFormat.OpenXml.Wordprocessing.TextDirectionValues, DocumentFormat.OpenXml, Version=2.15.0.0, Culture=neutral, PublicKeyToken=8fb06cb64d019a17]]",
      "Name": {
        "Name": "Val",
        "XmlName": "val",
        "NamespaceUri": "http://schemas.openxmlformats.org/wordprocessingml/2006/main",
        "NamespacePrefix": "w"
      }
    }
  ]
}